VastSite/__init__.py
VastSite/core.py
vastsite-1.7.1.dist-info/LICENSE
vastsite-1.7.1.dist-info/METADATA
vastsite-1.7.1.dist-info/WHEEL
vastsite-1.7.1.dist-info/top_level.txt
vastsite-1.7.1.dist-info/RECORD
