Metadata-Version: 2.1
Name: vastsite
Version: 1.7.1
Summary: A simple Python package to simplify Flask web app development.
Home-page: https://github.com/your_username/flask_easy
Author: Mingde Yang
Author-email: yangsilicon9@gmail.com
License: UNKNOWN
Platform: UNKNOWN
Classifier: License :: OSI Approved :: MIT License
Classifier: Programming Language :: Python :: 3
Classifier: Programming Language :: Python :: 3.7
Classifier: Programming Language :: Python :: 3.8
Classifier: Programming Language :: Python :: 3.9
License-File: LICENSE
Requires-Dist: Flask
Requires-Dist: speedtest-cli
